{
  "type": "minecraft:crafting_shapeless",
  "category": "misc",
  "ingredients": [
    {
      "item": "minecraft:bamboo"
    },
    {
      "item": "minecraft:bamboo"
    },
    {
      "item": "minecraft:bamboo"
    },
    {
      "item": "minecraft:bamboo"
    },
    {
      "item": "minecraft:gold_ingot"
    },
    {
      "item": "minecraft:copper_ingot"
    },
    {
      "item": "minecraft:copper_ingot"
    },
    {
      "item": "minecraft:copper_ingot"
    },
    {
      "item": "minecraft:copper_ingot"
    }
  ],
  "result": {
    "item": "rupecs_emblems:bamboo_emblem"
  }
}